.git_archival.txt
.gitattributes
.gitignore
.pre-commit-config.yaml
LICENSE
MANIFEST.in
README.md
dev-environment.yml
environment.yml
generate_interface_commands.py
mkdocs.yml
pyproject.toml
.github/FUNDING.yml
.github/actions/bmad-setup/action.yml
.github/actions/conda-setup/action.yml
.github/scripts/install_bmad.sh
.github/workflows/ci.yml
.github/workflows/gh-pages.yml
.github/workflows/lint.yml
.github/workflows/pypi_upload.yml
docs/development.md
docs/index.md
docs/installation.md
docs/usage.md
docs/api/plot-bokeh.md
docs/api/plot-mpl.md
docs/api/plot.md
docs/api/subprocesstao.md
docs/api/tao.md
docs/examples/advanced.ipynb
docs/examples/basic.ipynb
docs/examples/beam_track_progress_bar.ipynb
docs/examples/bunch.ipynb
docs/examples/fodo.ipynb
docs/examples/plot-bokeh-particles.ipynb
docs/examples/plot-bokeh-vars.ipynb
docs/examples/plot-bokeh.ipynb
docs/examples/plot-matplotlib.ipynb
docs/examples/special_parsers.ipynb
docs/overrides/main.html
docs/stylesheets/extra.css
old_docs/Makefile
old_docs/make.bat
old_docs/source/conf.py
old_docs/source/index.rst
old_docs/source/_static/under_construction.png
old_docs/source/_static/gui/figures/create_d1_1.png
old_docs/source/_static/gui/figures/create_d1_2.png
old_docs/source/_static/gui/figures/create_d1_3.png
old_docs/source/_static/gui/figures/create_d2_1.png
old_docs/source/_static/gui/figures/create_d2_2.png
old_docs/source/_static/gui/figures/edit_data_1.png
old_docs/source/_static/gui/figures/edit_data_2.png
old_docs/source/_static/gui/figures/globals_1.png
old_docs/source/_static/gui/figures/globals_2.png
old_docs/source/_static/gui/figures/lat_element_1_1.png
old_docs/source/_static/gui/figures/lat_element_1_2.png
old_docs/source/_static/gui/figures/lat_element_2_1.png
old_docs/source/_static/gui/figures/lat_element_2_2.png
old_docs/source/_static/gui/figures/lat_element_2_3.png
old_docs/source/_static/gui/figures/lat_element_multipoles_1.png
old_docs/source/_static/gui/figures/lat_element_multipoles_2.png
pytao.egg-info/PKG-INFO
pytao.egg-info/SOURCES.txt
pytao.egg-info/dependency_links.txt
pytao.egg-info/entry_points.txt
pytao.egg-info/requires.txt
pytao.egg-info/top_level.txt
