Metadata-Version: 2.4
Name: pytao
Version: 0.5.6
Summary: PyTao is the Python interface for Bmad's Tao
Author: David Sagan, Christopher Mayes, Hugo Slepicka
License:                     GNU GENERAL PUBLIC LICENSE
Project-URL: Homepage, https://www.classe.cornell.edu/bmad/tao.html
Project-URL: Documentation, https://bmad-sim.github.io/pytao/
Project-URL: Repository, https://github.com/bmad-sim/pytao
Project-URL: Issues, https://github.com/bmad-sim/pytao/issues
Classifier: Development Status :: 5 - Production/Stable
Classifier: Programming Language :: Python :: 3
Classifier: Programming Language :: Python :: 3.9
Classifier: Programming Language :: Python :: 3.10
Classifier: Programming Language :: Python :: 3.11
Classifier: Programming Language :: Python :: 3.12
Classifier: Topic :: Scientific/Engineering
Requires-Python: >=3.9
License-File: LICENSE
Provides-Extra: all
Requires-Dist: h5py; extra == "all"
Requires-Dist: ipython; extra == "all"
Requires-Dist: matplotlib; extra == "all"
Requires-Dist: numpy; extra == "all"
Requires-Dist: openpmd-beamphysics; extra == "all"
Requires-Dist: pexpect; extra == "all"
Requires-Dist: pydantic>=2; extra == "all"
Requires-Dist: tqdm; extra == "all"
Provides-Extra: test
Requires-Dist: pytest; extra == "test"
Requires-Dist: pytest-cov; extra == "test"
Dynamic: license-file
